Workbook

Sheet 12 Month Revenue
A1: 12 MONTH REVENUE FORECAST
A2: Particulars | C2: April | D2: May | E2: June | F2: July | G2: August | H2: September | I2: October | J2: November | K2: December | L2: January | M2: February | N2: March | O2: FY
C3: (Month-1) | D3: (Month-2) | E3: (Month-3) | F3: (Month-4) | G3: (Month-5) | H3: (Month-6) | I3: (Month-7) | J3: (Month-8) | K3: (Month-9) | L3: (Month-10) | M3: (Month-11) | N3: (Month-12) | O3: (Total)
A4: REVENUE ASSUMPTION | Q4: BROAD ASSUMPTIONS
A5: Organic Traffic | C5: =$R$5 -> 800 | D5: =C5*(1+$R$6) -> 944 | E5: =D5*(1+$R$6) -> 1113.92 | F5: =E5*(1+$R$6) -> 1314.4256 | G5: =F5*(1+$R$6) -> 1551.0222 | H5: =G5*(1+$R$6) -> 1830.2062 | I5: =H5*(1+$R$6) -> 2159.6433 | J5: =I5*(1+$R$6) -> 2548.3791 | K5: =J5*(1+$R$6) -> 3007.0874 | ... N5: =M5*(1+$R$6) -> 4940.7408 | O5: =SUM(C5:N5) -> 27944.856 | Q5: Organic Traffic – Month 1 (visitors) | R5: 800
A6: PaidTraffic | C6: =$R$7 -> 600 | D6: =C6*(1+$R$8) -> 672 | E6: =D6*(1+$R$8) -> 752.64 | F6: =E6*(1+$R$8) -> 842.9568 | G6: =F6*(1+$R$8) -> 944.11162 | H6: =G6*(1+$R$8) -> 1057.405 | I6: =H6*(1+$R$8) -> 1184.2936 | J6: =I6*(1+$R$8) -> 1326.4088 | K6: =J6*(1+$R$8) -> 1485.5779 | ... N6: =M6*(1+$R$8) -> 2087.13 | O6: =SUM(C6:N6) -> 14479.88 | Q6: Organic Traffic – Monthly Growth Rate | R6: =INDEX('Scenario Analysis'!C3:E3,MATCH('Scenario Analysis'!$A$9,'Scenario Analysis'!$C$2:$E$2,0)) -> 0.18
A7: Total Traffic | C7: =SUM(C5:C6) -> 1400 | D7: =SUM(D5:D6) -> 1616 | E7: =SUM(E5:E6) -> 1866.56 | F7: =SUM(F5:F6) -> 2157.3824 | G7: =SUM(G5:G6) -> 2495.1338 | H7: =SUM(H5:H6) -> 2887.6112 | I7: =SUM(I5:I6) -> 3343.9369 | J7: =SUM(J5:J6) -> 3874.788 | ... N7: =SUM(N5:N6) -> 7027.8708 | O7: =SUM(C7:N7) -> 42424.736 | Q7: Paid Traffic – Month 1 (visitors) | R7: 600
A8: Organic Conversion Rate | C8: =R9 -> 0.025 | D8: =C8*(1+$R$10) -> 0.025125 | E8: =D8*(1+$R$10) -> 0.025250625 | F8: =E8*(1+$R$10) -> 0.025376878 | G8: =F8*(1+$R$10) -> 0.025503763 | H8: =G8*(1+$R$10) -> 0.025631281 | I8: =H8*(1+$R$10) -> 0.025759438 | J8: =I8*(1+$R$10) -> 0.025888235 | K8: =J8*(1+$R$10) -> 0.026017676 | ... N8: =M8*(1+$R$10) -> 0.026409896 | Q8: Paid Traffic – Monthly Growth Rate | R8: =INDEX('Scenario Analysis'!C4:E4, MATCH('Scenario Analysis'!$A$9, 'Scenario Analysis'!$C$2:$E$2, 0)) -> 0.12
A9: Paid Conversion Rate | C9: =$R$11 -> 0.01 | D9: =C9*(1+$R$10) -> 0.01005 | E9: =D9*(1+$R$10) -> 0.01010025 | F9: =E9*(1+$R$10) -> 0.010150751 | G9: =F9*(1+$R$10) -> 0.010201505 | H9: =G9*(1+$R$10) -> 0.010252513 | I9: =H9*(1+$R$10) -> 0.010303775 | J9: =I9*(1+$R$10) -> 0.010355294 | K9: =J9*(1+$R$10) -> 0.01040707 | ... N9: =M9*(1+$R$10) -> 0.010563958 | Q9: Organic Conversion Rate – Month 1 | R9: 0.025
A10: Average Conversion Rate | C10: =AVERAGE(C8:C9) -> 0.0175 | D10: =AVERAGE(D8:D9) -> 0.0175875 | E10: =AVERAGE(E8:E9) -> 0.017675437 | F10: =AVERAGE(F8:F9) -> 0.017763815 | G10: =AVERAGE(G8:G9) -> 0.017852634 | H10: =AVERAGE(H8:H9) -> 0.017941897 | I10: =AVERAGE(I8:I9) -> 0.018031606 | J10: =AVERAGE(J8:J9) -> 0.018121764 | ... N10: =AVERAGE(N8:N9) -> 0.018486927 | Q10: Conversion Rate Monthly Improvement | R10: =INDEX('Scenario Analysis'!C5:E5, MATCH('Scenario Analysis'!$A$9, 'Scenario Analysis'!$C$2:$E$2, 0)) -> 0.005
A11: Organic Orders | C11: =ROUND(C5*C8,0) -> 20 | D11: =ROUND(D5*D8,0) -> 24 | E11: =ROUND(E5*E8,0) -> 28 | F11: =ROUND(F5*F8,0) -> 33 | G11: =ROUND(G5*G8,0) -> 40 | H11: =ROUND(H5*H8,0) -> 47 | I11: =ROUND(I5*I8,0) -> 56 | J11: =ROUND(J5*J8,0) -> 66 | ... N11: =ROUND(N5*N8,0) -> 130 | O11: =SUM(C11:N11) -> 725 | Q11: Paid Conversion Rate – Month 1 | R11: 0.01
A12: Paid Orders | C12: =ROUND(C6*C9,0) -> 6 | D12: =ROUND(D6*D9,0) -> 7 | E12: =ROUND(E6*E9,0) -> 8 | F12: =ROUND(F6*F9,0) -> 9 | G12: =ROUND(G6*G9,0) -> 10 | H12: =ROUND(H6*H9,0) -> 11 | I12: =ROUND(I6*I9,0) -> 12 | J12: =ROUND(J6*J9,0) -> 14 | ... N12: =ROUND(N6*N9,0) -> 22 | O12: =SUM(C12:N12) -> 151 | Q12: Avg Order Value – Months 1-6 | R12: 1499
A13: Total Orders | C13: =SUM(C11:C12) -> 26 | D13: =SUM(D11:D12) -> 31 | E13: =SUM(E11:E12) -> 36 | F13: =SUM(F11:F12) -> 42 | G13: =SUM(G11:G12) -> 50 | H13: =SUM(H11:H12) -> 58 | I13: =SUM(I11:I12) -> 68 | J13: =SUM(J11:J12) -> 80 | ... N13: =SUM(N11:N12) -> 152 | O13: =SUM(C13:N13) -> 876 | Q13: Avg Order Value – Months 7-12 | R13: 2999
A14: Order Details | Q14: Refund Rate | R14: =INDEX('Scenario Analysis'!C7:E7, MATCH('Scenario Analysis'!$A$9, 'Scenario Analysis'!$C$2:$E$2, 0)) -> 0.05
A15: Average Order Vaue | C15: =$R$12 -> 1499 | D15: =$R$12 -> 1499 | E15: =$R$12 -> 1499 | F15: =$R$12 -> 1499 | G15: =$R$12 -> 1499 | H15: =$R$12 -> 1499 | I15: =$R$13 -> 2999 | J15: =$R$13 -> 2999 | K15: =$R$13 -> 2999 | L15: =$R$13 -> 2999 | M15: =$R$13 -> 2999 | N15: =$R$13 -> 2999 | O15: =SUM(C15:N15) -> 26988 | Q15: Payment Processing Fee (%) | R15: 0.03
Q16: Platform Fee per Order | R16: 150
A17: COST ASSUMPTION | Q17: Paid Traffic (Cost per paid click) | R17: =INDEX('Scenario Analysis'!C6:E6, MATCH('Scenario Analysis'!$A$9, 'Scenario Analysis'!$C$2:$E$2, 0)) -> 20
A18: Variable Cost | Q18: Tax Rate | R18: 0.3
A19: Payment Processing Fees | C19: =$R$15*(C15*C13) -> 1169.22 | D19: =$R$15*(D15*D13) -> 1394.07 | E19: =$R$15*(E15*E13) -> 1618.92 | F19: =$R$15*(F15*F13) -> 1888.74 | G19: =$R$15*(G15*G13) -> 2248.5 | H19: =$R$15*(H15*H13) -> 2608.26 | I19: =$R$15*(I15*I13) -> 6117.96 | J19: =$R$15*(J15*J13) -> 7197.6 | ... N19: =$R$15*(N15*N13) -> 13675.44 | O19: =SUM(C19:N19) -> 67878.72 | Q19: Initial Cap | R19: 5000000
A20: Platform fees per order | C20: =$R$16*C13 -> 3900 | D20: =$R$16*D13 -> 4650 | E20: =$R$16*E13 -> 5400 | F20: =$R$16*F13 -> 6300 | G20: =$R$16*G13 -> 7500 | H20: =$R$16*H13 -> 8700 | I20: =$R$16*I13 -> 10200 | J20: =$R$16*J13 -> 12000 | ... N20: =$R$16*N13 -> 22800 | O20: =SUM(C20:N20) -> 131400
A21: Paid Traffic | C21: =$R$17*C6 -> 12000 | D21: =$R$17*D6 -> 13440 | E21: =$R$17*E6 -> 15052.8 | F21: =$R$17*F6 -> 16859.136 | G21: =$R$17*G6 -> 18882.232 | H21: =$R$17*H6 -> 21148.1 | I21: =$R$17*I6 -> 23685.872 | J21: =$R$17*J6 -> 26528.177 | ... N21: =$R$17*N6 -> 41742.6 | O21: =SUM(C21:N21) -> 289597.6
A22: Fixed Cost
A23: Salaries | C23: 120000 | D23: 120000 | E23: 120000 | F23: 120000 | G23: 120000 | H23: 120000 | I23: 150000 | J23: 150000 | K23: 150000 | L23: 150000 | M23: 150000 | N23: 150000 | O23: =SUM(C23:N23) -> 1620000
A24: Software&Subscriptions | C24: 20000 | D24: 20000 | E24: 20000 | F24: 20000 | G24: 20000 | H24: 20000 | I24: 20000 | J24: 20000 | K24: 20000 | L24: 20000 | M24: 20000 | N24: 20000 | O24: =SUM(C24:N24) -> 240000
A25: Other | C25: 10000 | D25: 10000 | E25: 10000 | F25: 10000 | G25: 10000 | H25: 10000 | I25: 15000 | J25: 15000 | K25: 15000 | L25: 15000 | M25: 15000 | N25: 15000 | O25: =SUM(C25:N25) -> 150000
A27: INCOME STATEMENT
A28: Revenue | C28: =C15*C13 -> 38974 | D28: =D15*D13 -> 46469 | E28: =E15*E13 -> 53964 | F28: =F15*F13 -> 62958 | G28: =G15*G13 -> 74950 | H28: =H15*H13 -> 86942 | I28: =I15*I13 -> 203932 | J28: =J15*J13 -> 239920 | ... N28: =N15*N13 -> 455848 | O28: =SUM(C28:N28) -> 2262624
A29: Less: Refund (5%) | C29: =C28*$R$14 -> 1948.7 | D29: =D28*$R$14 -> 2323.45 | E29: =E28*$R$14 -> 2698.2 | F29: =F28*$R$14 -> 3147.9 | G29: =G28*$R$14 -> 3747.5 | H29: =H28*$R$14 -> 4347.1 | I29: =I28*$R$14 -> 10196.6 | J29: =J28*$R$14 -> 11996 | ... N29: =N28*$R$14 -> 22792.4 | O29: =SUM(C29:N29) -> 113131.2
A30: COGS | C30: =SUM(C19:C20) -> 5069.22 | D30: =SUM(D19:D20) -> 6044.07 | E30: =SUM(E19:E20) -> 7018.92 | F30: =SUM(F19:F20) -> 8188.74 | G30: =SUM(G19:G20) -> 9748.5 | H30: =SUM(H19:H20) -> 11308.26 | I30: =SUM(I19:I20) -> 16317.96 | J30: =SUM(J19:J20) -> 19197.6 | ... N30: =SUM(N19:N20) -> 36475.44 | O30: =SUM(C30:N30) -> 199278.72
A31: Gross Profit | C31: =C28-C29-C30 -> 31956.08 | D31: =D28-D29-D30 -> 38101.48 | E31: =E28-E29-E30 -> 44246.88 | F31: =F28-F29-F30 -> 51621.36 | G31: =G28-G29-G30 -> 61454 | H31: =H28-H29-H30 -> 71286.64 | I31: =I28-I29-I30 -> 177417.44 | J31: =J28-J29-J30 -> 208726.4 | ... N31: =N28-N29-N30 -> 396580.16 | O31: =SUM(C31:N31) -> 1950214.1
A32: Gross Profit Margin % | C32: =C31/C28 -> 0.81993329 | D32: =D31/D28 -> 0.81993329 | E32: =E31/E28 -> 0.81993329 | F32: =F31/F28 -> 0.81993329 | G32: =G31/G28 -> 0.81993329 | H32: =H31/H28 -> 0.81993329 | I32: =I31/I28 -> 0.86998333 | J32: =J31/J28 -> 0.86998333 | ... O32: =O31/O28 -> 0.86192583
A34: Less: Operating Expenses | C34: =SUM(C21,C23,C24,C25) -> 162000 | D34: =SUM(D21,D23,D24,D25) -> 163440 | E34: =SUM(E21,E23,E24,E25) -> 165052.8 | F34: =SUM(F21,F23,F24,F25) -> 166859.14 | G34: =SUM(G21,G23,G24,G25) -> 168882.23 | H34: =SUM(H21,H23,H24,H25) -> 171148.1 | I34: =SUM(I21,I23,I24,I25) -> 208685.87 | J34: =SUM(J21,J23,J24,J25) -> 211528.18 | ... N34: =SUM(N21,N23,N24,N25) -> 226742.6 | O34: =SUM(C34:N34) -> 2299597.6
A36: EBT | C36: =C31-C34 -> -130043.92 | D36: =D31-D34 -> -125338.52 | E36: =E31-E34 -> -120805.92 | F36: =F31-F34 -> -115237.78 | G36: =G31-G34 -> -107428.23 | H36: =H31-H34 -> -99861.46 | I36: =I31-I34 -> -31268.432 | J36: =J31-J34 -> -2801.7769 | ... N36: =N31-N34 -> 169837.56 | O36: =SUM(C36:N36) -> -349383.52
A37: Less: Tax (30%) | C37: =IF(C36>0,C36*$R$18,"N/A") -> N/A | D37: =IF(D36>0,D36*$R$18,"N/A") -> N/A | E37: =IF(E36>0,E36*$R$18,"N/A") -> N/A | F37: =IF(F36>0,F36*$R$18,"N/A") -> N/A | G37: =IF(G36>0,G36*$R$18,"N/A") -> N/A | H37: =IF(H36>0,H36*$R$18,"N/A") -> N/A | I37: =IF(I36>0,I36*$R$18,"N/A") -> N/A | J37: =IF(J36>0,J36*$R$18,"N/A") -> N/A | ... N37: =IF(N36>0,N36*$R$18,"N/A") -> 50951.268 | O37: =SUM(C37:N37) -> 115020.76
A39: Profit/Loss | C39: =IFERROR(C36-C37,C36) -> -130043.92 | D39: =IFERROR(D36-D37,D36) -> -125338.52 | E39: =IFERROR(E36-E37,E36) -> -120805.92 | F39: =IFERROR(F36-F37,F36) -> -115237.78 | G39: =IFERROR(G36-G37,G36) -> -107428.23 | H39: =IFERROR(H36-H37,H36) -> -99861.46 | I39: =IFERROR(I36-I37,I36) -> -31268.432 | J39: =IFERROR(J36-J37,J36) -> -2801.7769 | ... N39: =IFERROR(N36-N37,N36) -> 118886.29 | O39: =SUM(C39:N39) -> -464404.27
A41: Unit Economics
A42: Paid CAC | C42: =C21/C12 -> 2000 | D42: =D21/D12 -> 1920 | E42: =E21/E12 -> 1881.6 | F42: =F21/F12 -> 1873.2373 | G42: =G21/G12 -> 1888.2232 | H42: =H21/H12 -> 1922.5546 | I42: =I21/I12 -> 1973.8227 | J42: =J21/J12 -> 1894.8698 | ... O42: =O21/O12 -> 1917.8649
A43: Avg Revenue per Order | C43: =C28/C13 -> 1499 | D43: =D28/D13 -> 1499 | E43: =E28/E13 -> 1499 | F43: =F28/F13 -> 1499 | G43: =G28/G13 -> 1499 | H43: =H28/H13 -> 1499 | I43: =I28/I13 -> 2999 | J43: =J28/J13 -> 2999 | ... O43: =O28/O13 -> 2582.9041
A44: Gross Profit per Order | C44: =C31/C13 -> 1229.08 | D44: =D31/D13 -> 1229.08 | E44: =E31/E13 -> 1229.08 | F44: =F31/F13 -> 1229.08 | G44: =G31/G13 -> 1229.08 | H44: =H31/H13 -> 1229.08 | I44: =I31/I13 -> 2609.08 | J44: =J31/J13 -> 2609.08 | ... O44: =O31/O13 -> 2226.2718
A45: CAC Payback Period (months) | C45: =C42/C44 -> 1.6272334 | D45: =D42/D44 -> 1.562144 | E45: =E42/E44 -> 1.5309012 | F45: =F42/F44 -> 1.5240972 | G45: =G42/G44 -> 1.5362899 | H45: =H42/H44 -> 1.5642225 | I45: =I42/I44 -> 0.75652057 | J45: =J42/J44 -> 0.72625975 | ... O45: =O42/O44 -> 0.86146935

Sheet Summary
A1: SkillMaxx | FY 2025 Summary Dashboard
A3: Key Performance Indicator | B3: FY 2025 Total
A4: Total Visitors | B4: ='12 Month Revenue'!$O$7 -> 42424.736
A5: Total Orders | B5: ='12 Month Revenue'!$O$13 -> 876
A6: Gross Revenue | B6: ='12 Month Revenue'!$O$28 -> 2262624
A7: Gross Profit | B7: ='12 Month Revenue'!$O$31 -> 1950214.1
A8: Gross Margin % | B8: ='12 Month Revenue'!$O$32 -> 0.86192583
A9: Total OpEx | B9: ='12 Month Revenue'!$O$34 -> 2299597.6
A10: EBIT | B10: ='12 Month Revenue'!$O$36 -> -349383.52
A11: Net Income / (Loss) | B11: ='12 Month Revenue'!$O$39 -> -464404.27
A12: Paid CAC | B12: ='12 Month Revenue'!$O$42 -> 1917.8649
A13: Avg Revenue per Order | B13: ='12 Month Revenue'!$O43 -> 2582.9041
A14: Gross Profit per Order | B14: ='12 Month Revenue'!$O44 -> 2226.2718
A15: CAC Payback Period (months) | B15: ='12 Month Revenue'!$O45 -> 0.86146935

Sheet Scenario Analysis
A1: Scenario Analysis| Bull/Base/Bear | FY 2025
A2: Headers | C2: Bear | D2: Base | E2: Bull
A3: Organic Traffic Growth Rate | C3: 0.12 | D3: 0.18 | E3: 0.22
A4: Paid Traffic Growth Rate | C4: 0.08 | D4: 0.12 | E4: 0.16
A5: Conversion Rate Monthly Improvement | C5: 0.0025 | D5: 0.005 | E5: 0.0075
A6: Paid Traffic Cost per Click | C6: 25 | D6: 20 | E6: 18
A7: Refund Rate | C7: 0.07 | D7: 0.05 | E7: 0.04
A8: Scenario Toggle ⬇
A9: Base

Sheet Cash Runway Analysis
A1: Cash Runway Analysis
A2: Particulars | C2: April | D2: May | E2: June | F2: July | G2: August | H2: September | I2: October | J2: November | K2: December | L2: January | M2: February | N2: March | O2: FY
C3: (Month-1) | D3: (Month-2) | E3: (Month-3) | F3: (Month-4) | G3: (Month-5) | H3: (Month-6) | I3: (Month-7) | J3: (Month-8) | K3: (Month-9) | L3: (Month-10) | M3: (Month-11) | N3: (Month-12) | O3: (Total)
A4: Opening Cash Balance | C4: ='12 Month Revenue'!R19 -> 5000000 | D4: =C6 -> 4869956.1 | E4: =D6 -> 4744617.6 | F4: =E6 -> 4623811.6 | G4: =F6 -> 4508573.9 | H4: =G6 -> 4401145.6 | I4: =H6 -> 4301284.2 | J4: =I6 -> 4270015.7 | K4: =J6 -> 4267214 | ... N4: =M6 -> 4416709.4
A5: Net Cash Flow | C5: ='12 Month Revenue'!C39 -> -130043.92 | D5: ='12 Month Revenue'!D39 -> -125338.52 | E5: ='12 Month Revenue'!E39 -> -120805.92 | F5: ='12 Month Revenue'!F39 -> -115237.78 | G5: ='12 Month Revenue'!G39 -> -107428.23 | H5: ='12 Month Revenue'!H39 -> -99861.46 | I5: ='12 Month Revenue'!I39 -> -31268.432 | J5: ='12 Month Revenue'!J39 -> -2801.7769 | ... N5: ='12 Month Revenue'!N39 -> 118886.29 | O5: =SUM(C5:N5) -> -464404.27
A6: Closing Cash Balance | C6: =C4+C5 -> 4869956.1 | D6: =D4+D5 -> 4744617.6 | E6: =E4+E5 -> 4623811.6 | F6: =F4+F5 -> 4508573.9 | G6: =G4+G5 -> 4401145.6 | H6: =H4+H5 -> 4301284.2 | I6: =I4+I5 -> 4270015.7 | J6: =J4+J5 -> 4267214 | ... N6: =N4+N5 -> 4535595.7 | O6: =N6 -> 4535595.7
A10: Runway Analysis Summary
A12: KPI's | B12: FY 2025 Total
A13: Initial Capital | B13: ='12 Month Revenue'!R19 -> 5000000
A14: Cash Balance at FY end | B14: =N6 -> 4535595.7
A15: Total Cash Burned (FY) | B15: =B13-B14 -> 464404.27
A16: Avg Monthly Burn (FY) | B16: =B15/12 -> 38700.356
A17: Runway at Current Burn Rate (months) | B17: =B13/B16 -> 129.19778

Sheet About&Notes
A1: ABOUT
A9: NOTES
A29: Made By~ Mayank Bharali
