Workbook

Sheet Assumptions & Inputs
A1: BROAD ASSUMPTIONS
A3: Company Details
A4: Company Name | B4: XYZ
A5: Currency | B5: Inr
A6: Model Date | B6: 46188
A8: Share Structure
A9: Total Authorized Shares | B9: 10000000
A10: Founding Shares | B10: 8500000
A11: ESOP Pool % | B11: 0.15
A12: ESOP Pool Share | B12: =B9*B11 -> 1500000
A14: Founder Details
A15: Founder 1 Name | B15: Mayank
A16: Founder 1 Share % | B16: 0.6
A17: Founder 1 Shares | B17: =$B$10*$B$16 -> 5100000
A18: Founder 2 Name | B18: Rathin
A19: Founder 2 Share % | B19: 0.4
A20: Founder 2 Shares | B20: =$B$10*$B$19 -> 3400000
A23: SEED Round
A24: Pre Money Valuation | B24: 50000000
A25: Investment Amount | B25: 10000000
A26: Post Money Valuation | B26: =SUM(B24:B25) -> 60000000
A27: Investor Name | B27: Lebron James
A28: Share Class | B28: Series Seed Preferred
A30: Series A Round
A31: Pre Money Valuation | B31: 250000000
A32: Investment Amount | B32: 50000000
A33: Post Money Valuation | B33: =SUM(B31:B32) -> 300000000
A34: Investor Name | B34: Stephen Curry
A35: Share Class | B35: Series A Preferred
A37: SAFE / Convertible Note
A38: SAFE Amount | B38: 2500000
A39: Discount Rate | B39: 0.2
A40: Valuation Cap | B40: 40000000
A41: SAFE Investor Name | B41: Jalen Brunson
A42: Conversion Round | B42: Seed

Sheet Founding Cap Table
A1: ="Founding Round Cap Table — "&'Assumptions & Inputs'!B4 -> Founding Round Cap Table — XYZ
A3: ROUND METRICS
A4: Total Authorized Shares | B4: ='Assumptions & Inputs'!B9 -> 10000000
A5: Total Issued Shares (Founders) | B5: ='Assumptions & Inputs'!B10 -> 8500000
A6: ESOP Pool (Reserved, Unissued) | B6: ='Assumptions & Inputs'!B12 -> 1500000
A7: Total Fully Diluted Shares | B7: =B5+B6 -> 10000000
A9: SHAREHOLDER TABLE
A10: Shareholder | B10: Role | C10: Share Class | D10: Shares Issued | E10: Shares Reserved (ESOP) | F10: % Ownership (Basic) | G10: % Ownership (Fully Diluted) | H10: Notes
A11: ='Assumptions & Inputs'!B15 -> Mayank | B11: CEO & Co-Founder | C11: Common Share | D11: ='Assumptions & Inputs'!B17 -> 5100000 | E11: 0 | F11: =D11/D$15 -> 0.6 | G11: =D11/(D$15+E$13) -> 0.51 | H11: 4-Year Vesting, 1-Year Cliff
A12: ='Assumptions & Inputs'!B18 -> Rathin | B12: CTO & Co-Founder | C12: Common Share | D12: ='Assumptions & Inputs'!B20 -> 3400000 | E12: 0 | F12: =D12/D$15 -> 0.4 | G12: =D12/(D$15+E$13) -> 0.34 | H12: 4-Year Vesting, 1-Year Cliff
A13: ESOP Pool | B13: Reserved for Employees | C13: Common Share (Unissued) | D13: 0 | E13: ='Assumptions & Inputs'!B12 -> 1500000 | F13: — | G13: =E13/(D$15+E$13) -> 0.15 | H13: Unissued; Reserved for Future Grants
A15: TOTAL | D15: =D11+D12 -> 8500000 | E15: =E13 -> 1500000 | F15: =F11+F12 -> 1 | G15: =G11+G12+G13 -> 1

Sheet Seed Round
A1: ="Seed Round Cap Table — "&'Assumptions & Inputs'!B4 -> Seed Round Cap Table — XYZ
A3: SECTION 1 — SAFE / CONVERTIBLE NOTE CONVERSION
A4: Metric | B4: Value | C4: Formula / Notes
A5: SAFE Investor | B5: ='Assumptions & Inputs'!B41 -> Jalen Brunson
A6: SAFE Amount (₹) | B6: ='Assumptions & Inputs'!B38 -> 2500000
A7: Valuation Cap (₹) | B7: ='Assumptions & Inputs'!B40 -> 40000000
A8: Discount Rate | B8: ='Assumptions & Inputs'!B39 -> 0.2
A9: Converts At (Round) | B9: ='Assumptions & Inputs'!B42 -> Seed
A11: Pre-Seed Issued Shares | B11: ='Founding Cap Table'!D15 -> 8500000 | C11: Founders’ shares only (no ESOP)
A12: Seed Standard PPS (₹) | B12: ='Assumptions & Inputs'!B24/'Founding Cap Table'!D15 -> 5.8823529 | C12: = Pre-Money ÷ Pre-Seed Issued Shares
A13: Cap Conversion Price (₹) | B13: ='Assumptions & Inputs'!B40/'Founding Cap Table'!D15 -> 4.7058824 | C13: = Valuation Cap ÷ Pre-Seed Shares
A14: Discount Conversion Price (₹) | B14: =B12*(1-'Assumptions & Inputs'!B39) -> 4.7058824 | C14: = Seed PPS × (1 − Discount Rate)
A15: ★ Effective Conversion Price (₹) | B15: =MIN(B13,B14) -> 4.7058824 | C15: = MIN(Cap, Discount) → Investor-favourable price
A16: ★ SAFE Shares Issued | B16: =ROUND('Assumptions & Inputs'!B38/B15,0) -> 531250 | C16: = SAFE Amount ÷ Conversion Price
A18: SECTION 2 — SEED ROUND INVESTMENT
A19: Metric | B19: Value | C19: Formula / Notes
A20: Seed Investor | B20: ='Assumptions & Inputs'!B27 -> Lebron James
A21: Share Class | B21: ='Assumptions & Inputs'!B28 -> Series Seed Preferred
A22: Pre-Money Valuation (₹) | B22: ='Assumptions & Inputs'!B24 -> 50000000
A23: Investment Amount (₹) | B23: ='Assumptions & Inputs'!B25 -> 10000000
A24: Post-Money Valuation (₹) | B24: ='Assumptions & Inputs'!B26 -> 60000000
A25: ★ Price Per Share (₹) | B25: ='Assumptions & Inputs'!B24/'Founding Cap Table'!D15 -> 5.8823529 | C25: = Pre-Money ÷ Pre-Seed Issued Shares
A26: ★ New Seed Shares Issued | B26: =ROUND('Assumptions & Inputs'!B25/B25,0) -> 1700000 | C26: = Seed Investment ÷ PPS
A28: SECTION 3 — POST-SEED CAP TABLE
A29: Shareholder | B29: Role | C29: Share Class | D29: Pre-Round Shares | E29: New Shares | F29: Post-Round Shares | G29: % Ownership (Basic) | H29: % Ownership (FD) | I29: Notes
A30: ='Assumptions & Inputs'!B15 -> Mayank | B30: CEO & Co-Founder | C30: Common Share | D30: ='Founding Cap Table'!D11 -> 5100000 | E30: 0 | F30: =D30+E30 -> 5100000 | G30: =F30/($F$36-$F$32) -> 0.47524752 | H30: =F30/$F$36 -> 0.41696474 | I30: 4-Year Vesting, 1-Year Cliff
A31: ='Assumptions & Inputs'!B18 -> Rathin | B31: CTO & Co-Founder | C31: Common Share | D31: ='Founding Cap Table'!D12 -> 3400000 | E31: 0 | F31: =D31+E31 -> 3400000 | G31: =F31/($F$36-$F$32) -> 0.31683168 | H31: =F31/$F$36 -> 0.27797649 | I31: 4-Year Vesting, 1-Year Cliff
A32: ESOP Pool | B32: Reserved for Employees | C32: Common Share (Unissued) | D32: ='Founding Cap Table'!E13 -> 1500000 | E32: 0 | F32: =D32+E32 -> 1500000 | G32: — | H32: =F32/$F$36 -> 0.12263669 | I32: No change this round
A33: ='Assumptions & Inputs'!B41 -> Jalen Brunson | B33: SAFE Investor → Seed Preferred | C33: ='Assumptions & Inputs'!B28 -> Series Seed Preferred | D33: 0 | E33: =B16 -> 531250 | F33: =D33+E33 -> 531250 | G33: =F33/($F$36-$F$32) -> 0.04950495 | H33: =F33/$F$36 -> 0.043433827 | I33: SAFE Conversion (see Sec. 1)
A34: ='Assumptions & Inputs'!B27 -> Lebron James | B34: Seed Investor | C34: ='Assumptions & Inputs'!B28 -> Series Seed Preferred | D34: 0 | E34: =B26 -> 1700000 | F34: =D34+E34 -> 1700000 | G34: =F34/($F$36-$F$32) -> 0.15841584 | H34: =F34/$F$36 -> 0.13898825
A36: TOTAL | D36: =D30+D31+D32+D33+D34 -> 10000000 | E36: =E30+E31+E32+E33+E34 -> 2231250 | F36: =F30+F31+F32+F33+F34 -> 12231250 | G36: =G30+G31+G33+G34 -> 1 | H36: =H30+H31+H32+H33+H34 -> 1

Sheet Series A
A1: ="Series A Cap Table — "&'Assumptions & Inputs'!B4 -> Series A Cap Table — XYZ
A3: SECTION 1 — SERIES A ROUND INVESTMENT
A4: Metric | B4: Value | C4: Formula / Notes
A5: Series A Investor | B5: ='Assumptions & Inputs'!B34 -> Stephen Curry
A6: Share Class | B6: ='Assumptions & Inputs'!B35 -> Series A Preferred
A7: Pre-Money Valuation (₹) | B7: ='Assumptions & Inputs'!B31 -> 250000000
A8: Investment Amount (₹) | B8: ='Assumptions & Inputs'!B32 -> 50000000
A9: Post-Money Valuation (₹) | B9: ='Assumptions & Inputs'!B33 -> 300000000
A11: Post-Seed Fully Diluted Shares | B11: ='Seed Round'!F36 -> 12231250 | C11: All shares incl. ESOP, post-Seed
A12: ★ Price Per Share (₹) | B12: ='Assumptions & Inputs'!B31/'Seed Round'!F36 -> 20.439448 | C12: = Pre-Money ÷ Post-Seed FD Shares
A13: ★ New Series A Shares Issued | B13: =ROUND('Assumptions & Inputs'!B32/B12,0) -> 2446250 | C13: = Series A Investment ÷ PPS
A15: SECTION 2 — POST-SERIES A CAP TABLE
A16: Shareholder | B16: Role | C16: Share Class | D16: Post-Seed Shares | E16: New Shares (Series A) | F16: Post-Series A Shares | G16: % Ownership (Basic) | H16: % Ownership (FD) | I16: Notes
A17: ='Assumptions & Inputs'!B15 -> Mayank | B17: CEO & Co-Founder | C17: Common Share | D17: ='Seed Round'!F30 -> 5100000 | E17: 0 | F17: =D17+E17 -> 5100000 | G17: =F17/($F$24-$F$19) -> 0.38702334 | H17: =F17/$F$24 -> 0.34747062 | I17: 4-Year Vesting, 1-Year Cliff
A18: ='Assumptions & Inputs'!B18 -> Rathin | B18: CTO & Co-Founder | C18: Common Share | D18: ='Seed Round'!F31 -> 3400000 | E18: 0 | F18: =D18+E18 -> 3400000 | G18: =F18/($F$24-$F$19) -> 0.25801556 | H18: =F18/$F$24 -> 0.23164708 | I18: 4-Year Vesting, 1-Year Cliff
A19: ESOP Pool | B19: Reserved for Employees | C19: Common Share (Unissued) | D19: ='Seed Round'!F32 -> 1500000 | E19: 0 | F19: =D19+E19 -> 1500000 | G19: — | H19: =F19/$F$24 -> 0.10219724 | I19: No change
A20: ='Assumptions & Inputs'!B41 -> Jalen Brunson | B20: SAFE / Seed Preferred | C20: ='Assumptions & Inputs'!B28 -> Series Seed Preferred | D20: ='Seed Round'!F33 -> 531250 | E20: 0 | F20: =D20+E20 -> 531250 | G20: =F20/($F$24-$F$19) -> 0.040314931 | H20: =F20/$F$24 -> 0.036194856
A21: ='Assumptions & Inputs'!B27 -> Lebron James | B21: Seed Preferred | C21: ='Assumptions & Inputs'!B28 -> Series Seed Preferred | D21: ='Seed Round'!F34 -> 1700000 | E21: 0 | F21: =D21+E21 -> 1700000 | G21: =F21/($F$24-$F$19) -> 0.12900778 | H21: =F21/$F$24 -> 0.11582354
A22: ='Assumptions & Inputs'!B34 -> Stephen Curry | B22: Series A Investor | C22: ='Assumptions & Inputs'!B35 -> Series A Preferred | D22: 0 | E22: =B13 -> 2446250 | F22: =D22+E22 -> 2446250 | G22: =F22/($F$24-$F$19) -> 0.1856384 | H22: =F22/$F$24 -> 0.16666667
A24: TOTAL | D24: =D17+D18+D19+D20+D21+D22 -> 12231250 | E24: =E17+E18+E19+E20+E21+E22 -> 2446250 | F24: =F17+F18+F19+F20+F21+F22 -> 14677500 | G24: =G17+G18+G20+G21+G22 -> 1 | H24: =H17+H18+H19+H20+H21+H22 -> 1

Sheet Dilution Summary
A1: ="Dilution Summary — "&'Assumptions & Inputs'!B4 -> Dilution Summary — XYZ
A3: ROUND SUMMARY
A4: Round | B4: Pre-Money (₹) | C4: Investment (₹) | D4: Post-Money (₹) | E4: PPS (₹) | F4: Total FD Shares | G4: New Shares Issued
A5: Founding | B5: — | C5: — | D5: — | E5: — | F5: ='Founding Cap Table'!B7 -> 10000000 | G5: ='Founding Cap Table'!D15 -> 8500000
A6: Seed Round | B6: ='Assumptions & Inputs'!B24 -> 50000000 | C6: ='Assumptions & Inputs'!B25 -> 10000000 | D6: ='Assumptions & Inputs'!B26 -> 60000000 | E6: ='Seed Round'!B25 -> 5.8823529 | F6: ='Seed Round'!F36 -> 12231250 | G6: ='Seed Round'!E36 -> 2231250
A7: Series A | B7: ='Assumptions & Inputs'!B31 -> 250000000 | C7: ='Assumptions & Inputs'!B32 -> 50000000 | D7: ='Assumptions & Inputs'!B33 -> 300000000 | E7: ='Series A'!B12 -> 20.439448 | F7: ='Series A'!F24 -> 14677500 | G7: ='Series A'!E24 -> 2446250
A9: OWNERSHIP % WATERFALL — FULLY DILUTED
A10: Shareholder | B10: Post-Founding | C10: Post-Seed | D10: Post-Series A | E10: Founder Dilution
A11: ='Assumptions & Inputs'!B15 -> Mayank | B11: ='Founding Cap Table'!G11 -> 0.51 | C11: ='Seed Round'!H30 -> 0.41696474 | D11: ='Series A'!H17 -> 0.34747062 | E11: =B11-D11 -> 0.16252938
A12: ='Assumptions & Inputs'!B18 -> Rathin | B12: ='Founding Cap Table'!G12 -> 0.34 | C12: ='Seed Round'!H31 -> 0.27797649 | D12: ='Series A'!H18 -> 0.23164708 | E12: =B12-D12 -> 0.10835292
A13: ESOP Pool | B13: ='Founding Cap Table'!G13 -> 0.15 | C13: ='Seed Round'!H32 -> 0.12263669 | D13: ='Series A'!H19 -> 0.10219724 | E13: —
A14: ='Assumptions & Inputs'!B41 -> Jalen Brunson | B14: — | C14: ='Seed Round'!H33 -> 0.043433827 | D14: ='Series A'!H20 -> 0.036194856 | E14: —
A15: ='Assumptions & Inputs'!B27 -> Lebron James | B15: — | C15: ='Seed Round'!H34 -> 0.13898825 | D15: ='Series A'!H21 -> 0.11582354 | E15: —
A16: ='Assumptions & Inputs'!B34 -> Stephen Curry | B16: — | C16: — | D16: ='Series A'!H22 -> 0.16666667 | E16: —
A18: TOTAL | B18: =B11+B12+B13 -> 1 | C18: =C11+C12+C13+C14+C15 -> 1 | D18: =D11+D12+D13+D14+D15+D16 -> 1
B21: ='Assumptions & Inputs'!B15 -> Mayank | C21: ='Assumptions & Inputs'!B18 -> Rathin | D21: ESOP Pool | E21: ='Assumptions & Inputs'!B41 -> Jalen Brunson | F21: ='Assumptions & Inputs'!B27 -> Lebron James | G21: ='Assumptions & Inputs'!B34 -> Stephen Curry
A22: Post-Founding | B22: =B11 -> 0.51 | C22: =B12 -> 0.34 | D22: =B13 -> 0.15 | E22: 0 | F22: 0 | G22: 0
A23: Post-Seed | B23: =C11 -> 0.41696474 | C23: =C12 -> 0.27797649 | D23: =C13 -> 0.12263669 | E23: =C14 -> 0.043433827 | F23: =C15 -> 0.13898825 | G23: 0
A24: Post-Series A | B24: =D11 -> 0.34747062 | C24: =D12 -> 0.23164708 | D24: =D13 -> 0.10219724 | E24: =D14 -> 0.036194856 | F24: =D15 -> 0.11582354 | G24: =D16 -> 0.16666667

Sheet Note
A1: NOTE
A15: Made By~ Mayank Bharali
